LICENSE
README.md
pyproject.toml
tracklist/__init__.py
tracklist/__main__.py
tracklist/model.py
tracklist/utils.py
tracklist.egg-info/PKG-INFO
tracklist.egg-info/SOURCES.txt
tracklist.egg-info/dependency_links.txt
tracklist.egg-info/entry_points.txt
tracklist.egg-info/top_level.txt
tracklist/aggregate/__init__.py
tracklist/aggregate/cat.py
tracklist/aggregate/merge.py
tracklist/format/__init__.py
tracklist/format/cuesheet.py
tracklist/format/tabular.py
tracklist/resolve/__init__.py
tracklist/resolve/ffprobe.py