Metadata-Version: 2.1
Name: tracklist
Version: 0.0.3
Summary: Library and CLI tool for processing tracklists
Project-URL: Homepage, https://github.com/fwcd/python-tracklist
Project-URL: Repository, https://github.com/fwcd/python-tracklist
Classifier: Topic :: Utilities
License-File: LICENSE
